tts_webui_extension/vocos/__init__.py
tts_webui_extension/vocos/main.py
tts_webui_extension_vocos-0.0.3.dist-info/licenses/LICENSE
tts_webui_extension_vocos-0.0.3.dist-info/METADATA
tts_webui_extension_vocos-0.0.3.dist-info/WHEEL
tts_webui_extension_vocos-0.0.3.dist-info/top_level.txt
tts_webui_extension_vocos-0.0.3.dist-info/RECORD
