Metadata-Version: 2.4
Name: tts_webui_extension.vocos
Version: 0.0.3
Summary: Vocos is a neural audio codec for high-quality audio compression and reconstruction
Home-page: https://github.com/rsxdalv/tts_webui_extension.vocos
Author: rsxdalv
Classifier: Programming Language :: Python :: 3
Classifier: License :: OSI Approved :: MIT License
Classifier: Operating System :: OS Independent
License-File: LICENSE
Requires-Dist: vocos==0.1.0
Dynamic: author
Dynamic: classifier
Dynamic: description
Dynamic: description-content-type
Dynamic: home-page
Dynamic: license-file
Dynamic: requires-dist
Dynamic: summary
